[
	{
	  "Name": "Suwa Station",
	  "Image": "suwastationbandpicture.png",
	  "Text": "",
	  "Link": "https://soundcloud.com/user-501753111-169752075,https://www.instagram.com/suwa.station",
	  "Type": "",
	  "Artists": ""
	},
	{
	  "Name": "Liquid Silk",
	  "Image": "LiquidSilk.jpg",
	  "Text": "",
	  "Link": "liquidsilk.bandcamp.com",
	  "Type": "",
	  "Artists": ""
	},
	{
	  "Name": "ST. TOUPET",
	  "Image": "203035915_103327125333242_642464962097665453_n.jpg",
	  "Text": "",
	  "Link": "https://www.facebook.com/St-Toupet-103324645333490",
	  "Type": "",
	  "Artists": ""
	},
	{
	  "Name": "14-4 Liquor Store",
	  "Image": "226864516_2630345633934679_6474725821824210958_n.jpg",
	  "Text": "",
	  "Link": "https://www.instagram.com/14_4_liquorstore/,https://www.facebook.com/144LiquorStore,https://14-4liquorstore.bandcamp.com/",
	  "Type": "",
	  "Artists": ""
	},
	{
	  "Name": "Kaskadeur",
	  "Image": "KASKADEUR_promo_by_DenisLaner.jpg",
	  "Text": "",
	  "Link": "https://www.kaskadeur.net/,https://www.instagram.com/kaskadeur.band/,https://www.facebook.com/kaskadeur,https://kaskadeur.bandcamp.com/",
	  "Type": "",
	  "Artists": ""
	},
	{
	  "Name": "OYA Band",
	  "Image": "OYABand.jpg",
	  "Text": "",
	  "Link": "https://oya.one/,https://www.facebook.com/oyaroots,https://www.youtube.com/channel/UCS8EE7yVgY63Z7LpkRRVVZQ/featured",
	  "Type": "",
	  "Artists": ""
	},
	{
	  "Name": "Trash Ketchum",
	  "Image": "TrashKetchum.jpeg",
	  "Text": "",
	  "Link": "",
	  "Type": "",
	  "Artists": ""
	},
	{
	  "Name": "Planet Obsolescence",
	  "Image": "93032080_3348166255198360_4914971972938498048_n.jpg",
	  "Text": "",
	  "Link": "https://stadler-metall.de/www-planet-obsolescence-com,https://m.facebook.com/#!/planetobsolescence/",
	  "Type": "",
	  "Artists": ""
	},
	{
	  "Name": "DJ Hornhaut Live Band",
	  "Image": "DJHornhautLiveBand.jpg",
	  "Text": "",
	  "Link": "https://www.instagram.com/djhornhaut/,https://djhornhaut.bandcamp.com/ ",
	  "Type": "",
	  "Artists": ""
	},
	{
	  "Name": "IVORY KASHINSKY",
	  "Image": "IvoryKashinsky.jpeg",
	  "Text": "",
	  "Link": "https://ivorykashinsky.bandcamp.com/releases,https://open.spotify.com/album/0LGxTbu9J5t0dislbbU2H0?si=DVZEjhYORliAFzMk-1pHcg&dl_branch=1,https://www.instagram.com/ivory_kashinsky/",
	  "Type": "",
	  "Artists": ""
	},
	{
	  "Name": "Nifty5",
	  "Image": "",
	  "Text": "",
	  "Link": "",
	  "Type": "",
	  "Artists": ""
	},
	{
	  "Name": "phyt",
	  "Image": "",
	  "Text": "",
	  "Link": "https://m.facebook.com/phytleipzig/",
	  "Type": "",
	  "Artists": ""
	},
	{
	  "Name": "MXM & Pavel",
	  "Image": "MXMPavel.jpg",
	  "Text": "",
	  "Link": "https://www.instagram.com/mxmundpavel/",
	  "Type": "",
	  "Artists": ""
	},
	{
	  "Name": "Karakum (live)",
	  "Image": "Karakum.jpg",
	  "Text": "",
	  "Link": "https://www.karakum-techno.de/,https://soundcloud.com/karakum-techno,https://www.instagram.com/karakum_live",
	  "Type": "",
	  "Artists": ""
	},
	{
	  "Name": "VISION",
	  "Image": "VISION.jpg",
	  "Text": "",
	  "Link": "https://www.instagram.com/vision.musicofficial",
	  "Type": "",
	  "Artists": ""
	},
	{
	  "Name": "Le Friseur",
	  "Image": "lefriseur.png",
	  "Text": "",
	  "Link": "https://soundcloud.com/elfriseur",
	  "Type": "",
	  "Artists": ""
	},
	{
	  "Name": "Impala",
	  "Image": "ImpalaakaWagnerLuuv.png",
	  "Text": "",
	  "Link": "https://soundcloud.com/impala_wagnerluuv",
	  "Type": "",
	  "Artists": ""
	},
	{
	  "Name": "Herr Sakas",
	  "Image": "ImpalaakaWagnerLuuv.png",
	  "Text": "",
	  "Link": "https://soundcloud.com/hr-sakas",
	  "Type": "",
	  "Artists": ""
	},
	{
	  "Name": "Mara",
	  "Image": "Mara.png",
	  "Text": "",
	  "Link": "https://soundcloud.com/gysey_gregorowitsch",
	  "Type": "",
	  "Artists": ""
	},
	{
	  "Name": "Syndrum",
	  "Image": "Syndrum.png",
	  "Text": "",
	  "Link": "https://soundcloud.com/niclas-helbig-1",
	  "Type": "",
	  "Artists": ""
	},
	{
	  "Name": "DAITO",
	  "Image": "DAITO.png",
	  "Text": "",
	  "Link": "https://soundcloud.com/daitoberlin",
	  "Type": "",
	  "Artists": ""
	},
	{
	  "Name": "Dakama",
	  "Image": "Dakama.png",
	  "Text": "",
	  "Link": "https://soundcloud.com/dakama",
	  "Type": "",
	  "Artists": ""
	},
	{
	  "Name": "böfek",
	  "Image": "böfek.png",
	  "Text": "",
	  "Link": "https://soundcloud.com/caspartimm",
	  "Type": "",
	  "Artists": ""
	},
	{
	  "Name": "CVO",
	  "Image": "Promo_PicCVO.JPG",
	  "Text": "",
	  "Link": "https://soundcloud.com/casimirvonoettingen,https://www.facebook.com/der.casimir.von.oettingen,https://www.instagram.com/cvo_bladehouse/",
	  "Type": "",
	  "Artists": ""
	},
	{
	  "Name": "10 Mark DJ Team",
	  "Image": "10markdjteam.png",
	  "Text": "",
	  "Link": "https://soundcloud.com/10-mark-dj-team",
	  "Type": "",
	  "Artists": ""
	},
	{
	  "Name": "Lisa Filou b2b Ring and Dorf",
	  "Image": "LisaFilou.jpg",
	  "Text": "",
	  "Link": "https://soundcloud.com/lisafilou",
	  "Type": "multiple",
	  "Artists": [{
		"Name": "Lisa Filou",
		"Image": "LisaFilou.jpg",
		"Text": "",
		"Link": "https://soundcloud.com/lisafilou,ttps://www.facebook.com/LisaFilou.RamSchakl,https://www.instagram.com/lisa_filou_t/",
		"Type": "",
		"Artists": ""
	  },
	  {
		"Name": "Ring and Dorf",
		"Image": "RingDorf.png",
		"Text": "",
		"Link": "https://soundcloud.com/ringanddorf",
		"Type": "",
		"Artists": ""
	  }
	  ]
	},
	{
	  "Name": "Burninski",
	  "Image": "Burninski.jpeg",
	  "Text": "",
	  "Link": "https://soundcloud.com/burninski,https://www.instagram.com/_burninski",
	  "Type": "",
	  "Artists": ""
	},
	{
	  "Name": "Elias Goldmund",
	  "Image": "EliasGoldmund.jpg",
	  "Text": "",
	  "Link": "https://soundcloud.com/goldmund01,https://www.facebook.com/Elias-Goldmund-116986411668088,https://www.instagram.com/elias_goldmund/",
	  "Type": "",
	  "Artists": ""
	},
	{
	  "Name": "Ellosophy",
	  "Image": "Ellosophy.jpeg",
	  "Text": "",
	  "Link": "https://soundcloud.com/ellosophy,https://www.facebook.com/Ellosophy.live,https://www.instagram.com/ellosophy__/,https://www.youtube.com/watch?v=dZYd5gw4r88&t=1856s",
	  "Type": "",
	  "Artists": ""
	},
	{
	  "Name": "Lukov",
	  "Image": "",
	  "Text": "",
	  "Link": "https://www.instagram.com/lukov__/,https://soundcloud.com/lukovski",
	  "Type": "",
	  "Artists": ""
	},
	{
	  "Name": "LENI",
	  "Image": "",
	  "Text": "",
	  "Link": "https://soundcloud.com/lenilow,https://www.facebook.com/itsleni",
	  "Type": "",
	  "Artists": ""
	},
	{
	  "Name": "kluntje",
	  "Image": "",
	  "Text": "",
	  "Link": "https://soundcloud.com/kluntjele",
	  "Type": "",
	  "Artists": ""
	},
	{
	  "Name": "Brigade",
	  "Image": "BrigadePic1.JPG",
	  "Text": "",
	  "Link": "http://instagram.com/brigade_international/,http://soundcloud.com/brigadeberlin,http://facebook.com/brigadeberlin",
	  "Type": "",
	  "Artists": ""
	},
	{
	  "Name": "Gina Sabatini",
	  "Image": "",
	  "Text": "",
	  "Link": "https://soundcloud.com/gina-sabatini,https://www.facebook.com/sabatinigina,https://www.instagram.com/gina.sabatini/",
	  "Type": "",
	  "Artists": ""
	},
	{
	  "Name": "Igor Amore",
	  "Image": "IgorAmore.jpg",
	  "Text": "",
	  "Link": "https://soundcloud.com/igor-amore-official,https://www.instagram.com/igor_amore/",
	  "Type": "",
	  "Artists": ""
	},
	{
	  "Name": "Faber",
	  "Image": "",
	  "Text": "",
	  "Link": "https://soundcloud.com/faberbeatz,https://open.spotify.com/artist/1mv80noLQq4X6hQN9AeRuc,https://www.facebook.com/FaberBerlin IG:https://www.instagram.com/lil1won/",
	  "Type": "",
	  "Artists": ""
	},
	{
	  "Name": "nΦra & kueksen",
	  "Image": "noraküksen.jpeg",
	  "Text": "",
	  "Link": "",
	  "Type": "multiple",
	  "Artists": [{
		"Name": "nΦra",
		"Image": "noraküksen.jpeg",
		"Text": "",
		"Link": "https://soundcloud.com/einfachnora",
		"Type": "",
		"Artists": ""
	  },
	  {
		"Name": "kueksen",
		"Image": "noraküksen.jpeg",
		"Text": "",
		"Link": "https://soundcloud.com/kueksen",
		"Type": "",
		"Artists": ""
	  }]
	},
	{
	  "Name": "Frida Darko & Atric",
	  "Image": "",
	  "Text": "",
	  "Link": "",
	  "Type": "multiple",
	  "Artists": [{
		"Name": "Frida Darko",
		"Image": "",
		"Text": "",
		"Link": "https://soundcloud.com/frida-darko,https://.spotify.com/artist/6aRhznYRuDprkHf1z0Jgws",
		"Type": "",
		"Artists": ""
	  },
	  {
		"Name": "Atric",
		"Image": "",
		"Text": "",
		"Link": "https://soundcloud.com/casanova_tony,https://.spotify.com/artist/5nvhpnFpC7rsQ0mWDNx4bn",
		"Type": "",
		"Artists": ""
	  }]
	},
	{
	  "Name": "Käptn 12 & Düsentrieb",
	  "Image": "Käptn12Düsentrieb.jpg",
	  "Text": "",
	  "Link": "https://www.facebook.com/Kaeptn12Duesentrieb,https://soundcloud.com/12imhaus",
	  "Type": "",
	  "Artists": ""
	},
	{
	  "Name": "Dürerstuben",
	  "Image": "Dürerstuben.png",
	  "Text": "",
	  "Link": "https://duererstuben.com/,https://www.instagram.com/duererstuben",
	  "Type": "",
	  "Artists": ""
	},
	{
	  "Name": "Glenn Shaw",
	  "Image": "GlennShaw.JPG",
	  "Text": "",
	  "Link": "https://soundcloud.com/glenn_shaw",
	  "Type": "",
	  "Artists": ""
	},
	{
	  "Name": "slow revolt",
	  "Image": "",
	  "Text": "",
	  "Link": "https://soundcloud.com/slowrevolt",
	  "Type": "",
	  "Artists": ""
	},
	{
	  "Name": "Pavelo Promillo",
	  "Image": "PaveloPromillo.jpg",
	  "Text": "",
	  "Link": "https://www.instagram.com/pavelo.promillo",
	  "Type": "",
	  "Artists": ""
	},
	{
	  "Name": "Boris Schnell",
	  "Image": "BorisSchnell.png",
	  "Text": "",
	  "Link": "",
	  "Type": "",
	  "Artists": ""
	},
	{
	  "Name": "MataHari & Volker Arnold",
	  "Image": "mataharib2bvolkerarnold.jpeg",
	  "Text": "",
	  "Link": "",
	  "Type": "multiple",
	  "Artists": [{
		"Name": "MataHari",
		"Image": "mataharib2bvolkerarnold.jpeg",
		"Text": "",
		"Link": "https://soundcloud.com/mataharry",
		"Type": "",
		"Artists": ""
	  },
	  {
		"Name": "Volker Arnold",
		"Image": "mataharib2bvolkerarnold.jpeg",
		"Text": "",
		"Link": "https://soundcloud.com/varnold",
		"Type": "",
		"Artists": ""
	  }]
	},
	{
	  "Name": "Iffie",
	  "Image": "Iffie.jpeg",
	  "Text": "",
	  "Link": "https://soundcloud.com/iffie,https://soundcloud.com/intotheabysspodcastseries,https://www.facebook.com/Iffie-401970459957896,https://www.facebook.com/intotheabysspodcastseries",
	  "Type": "",
	  "Artists": ""
	},
	{
	  "Name": "Bastian Balders",
	  "Image": "BastianBalders.jpeg",
	  "Text": "",
	  "Link": "https://soundcloud.com/bastianbalders,https://bastianbalders.bandcamp.com,https://www.facebook.com/bastianbalders,https://www.instagram.com/bastianbalders",
	  "Type": "",
	  "Artists": ""
	},
	{
	  "Name": "TØSCHE",
	  "Image": "TOSCHE.jpg",
	  "Text": "",
	  "Link": "https://soundcloud.com/dj_tosche,https://www.facebook.com/dj.tosche,https://www.instagram.com/tosche___/",
	  "Type": "",
	  "Artists": ""
	},
	{
	  "Name": "chacha",
	  "Image": "chacha.jpg",
	  "Text": "",
	  "Link": "https://soundcloud.com/chacha_pvc,https://www.instagram.com/cha.chahh/",
	  "Type": "",
	  "Artists": ""
	},
	{
	  "Name": "Jamida",
	  "Image": "Jamida.jpg",
	  "Text": "",
	  "Link": "https://soundcloud.com/ja-mida,https://www.instagram.com/jamidavalian",
	  "Type": "",
	  "Artists": ""
	},
	{
	  "Name": "s.ra",
	  "Image": "s.ra.jpg",
	  "Text": "",
	  "Link": "https://soundcloud.com/s_ra,https://ra.co/dj/sra-de,https://www.facebook.com/s.ra.ifz,https://www.instagram.com/s.ra_ifz/",
	  "Type": "",
	  "Artists": ""
	},
	{
	  "Name": "Sonnensysteme",
	  "Image": "Sonnensysteme.jpg",
	  "Text": "",
	  "Link": "https://www.facebook.com/diesonnensysteme,https://soundcloud.com/diesonnensysteme,https://www.instagram.com/sonnensysteme,http://www.residentadvisor.net/dj/sonnensysteme",
	  "Type": "",
	  "Artists": ""
	},
	{
	  "Name": "Mila Stern",
	  "Image": "",
	  "Text": "",
	  "Link": "https://soundcloud.com/mila-stern,https://www.instagram.com/milastern1234/",
	  "Type": "",
	  "Artists": ""
	},
	{
	  "Name": "Super Flu",
	  "Image": "SuperFlu.jpg",
	  "Text": "",
	  "Link": "https://super-flu.de/",
	  "Type": "",
	  "Artists": ""
	},
	{
	  "Name": "kiara",
	  "Image": "",
	  "Text": "",
	  "Link": "https://soundcloud.com/kiaralpz",
	  "Type": "",
	  "Artists": ""
	},
	{
	  "Name": "Delia Plangg & Martin Saupe",
	  "Image": "",
	  "Text": "",
	  "Link": "",
	  "Type": "multiple",
	  "Artists": [{
		  "Name": "Delia Plangg",
		  "Image": "",
		  "Text": "",
		  "Link": "soundcloud.com/delia-plangg,facebook.com/delia-plangg",
		  "Type": "",
		  "Artists": ""
	  },
	  {
			"Name": "Martin Saupe",
			"Text": "",
			"Image": "",
			"Link": "soundcloud.com/msaupe,facebook.com/msaupe",
			"Type": "",
			"Artists": ""
	  }]
	},
	{
	  "Name": "Nina Hepburn",
	  "Image": "NinaHepburn.jpg",
	  "Text": "",
	  "Link": "https://www.instagram.com/ninahepburn_/,https://soundcloud.com/nina-hepburn,http://ninahepburn.com/",
	  "Type": "",
	  "Artists": ""
	},
	{
	  "Name": "Schense",
	  "Image": "",
	  "Text": "",
	  "Link": "https://soundcloud.com/Schense",
	  "Type": "",
	  "Artists": ""
	},
	{
	  "Name": "garstique",
	  "Image": "",
	  "Text": "",
	  "Link": "https://www.instagram.com/garstique/,https://soundcloud.com/garstique",
	  "Type": "",
	  "Artists": ""
	},
	{
	  "Name": "Hanoj & Ecdyson",
	  "Image": "HanojEcdyson.jpg",
	  "Text": "",
	  "Link": "",
	  "Type": "",
	  "Artists": ""
	},
	{
	  "Name": "Adamson",
	  "Image": "adamson.jpg",
	  "Text": "",
	  "Link": "",
	  "Type": "",
	  "Artists": ""
	},
	{
	  "Name": "Cotufa",
	  "Image": "",
	  "Text": "",
	  "Link": "",
	  "Type": "",
	  "Artists": ""
	},
	{
	  "Name": "Benin",
	  "Image": "benin.jpg",
	  "Text": "",
	  "Link": "",
	  "Type": "",
	  "Artists": ""
	},
	{
	  "Name": "Onero",
	  "Image": "Onero.PNG",
	  "Text": "",
	  "Link": "www.soundcloud.com/onero-music",
	  "Type": "",
	  "Artists": ""
	},
	{
	  "Name": "Yondo And Lorca",
	  "Image": "YondoAndLorca.png",
	  "Text": "",
	  "Link": "",
	  "Type": "",
	  "Artists": ""
	},
	{
	  "Name": "Nutaq",
	  "Image": "Nutaq.jpg",
	  "Text": "",
	  "Link": "",
	  "Type": "",
	  "Artists": ""
	},
	{
	  "Name": "Dschagganaut",
	  "Image": "Dschagganaut.PNG",
	  "Text": "",
	  "Link": "",
	  "Type": "",
	  "Artists": ""
	},
	{
	  "Name": "Anoxia",
	  "Image": "Anoxia.jpg",
	  "Text": "",
	  "Link": "https://soundcloud.com/l300decart",
	  "Type": "",
	  "Artists": ""
	},
	{
	  "Name": "Alsan",
	  "Image": "Alsan.jpg",
	  "Text": "",
	  "Link": "",
	  "Type": "",
	  "Artists": ""
	},
	{
	  "Name": "JusTech",
	  "Image": "JusTech.jpg",
	  "Text": "",
	  "Link": "",
	  "Type": "",
	  "Artists": ""
	},
	{
	  "Name": "Sun Wu Kong",
	  "Image": "SunWuKong.jpg",
	  "Text": "",
	  "Link": "",
	  "Type": "",
	  "Artists": ""
	},
	{
	  "Name": "El Puno",
	  "Image": "ElPuno.JPG",
	  "Text": "",
	  "Link": "",
	  "Type": "",
	  "Artists": ""
	},
	{
	  "Name": "Omikron",
	  "Image": "Omikron.jpg",
	  "Text": "",
	  "Link": "",
	  "Type": "",
	  "Artists": ""
	},
	{
	  "Name": "Perkins",
	  "Image": "Perkins.png",
	  "Text": "",
	  "Link": "",
	  "Type": "",
	  "Artists": ""
	},
	{
	  "Name": "Possebility",
	  "Image": "Possebility.jpg",
	  "Text": "",
	  "Link": "",
	  "Type": "",
	  "Artists": ""
	},
	{
	  "Name": "Eritas",
	  "Image": "Eritas-LIVE-.jpg",
	  "Text": "",
	  "Link": "",
	  "Type": "",
	  "Artists": ""
	},
	{
	  "Name": "Hitodama",
	  "Image": "Hitodama.jpg",
	  "Text": "",
	  "Link": "https://soundcloud.com/hotzenplotz-hotzenplotz",
	  "Type": "",
	  "Artists": ""
	},
	{
	  "Name": "Act One",
	  "Image": "ActOne-LIVE-.PNG",
	  "Text": "",
	  "Link": "",
	  "Type": "",
	  "Artists": ""
	},
	{
	  "Name": "Entheon",
	  "Image": "Entheon.jpg",
	  "Text": "",
	  "Link": "",
	  "Type": "",
	  "Artists": ""
	},
	{
	  "Name": "Touchaman",
	  "Image": "Tochaman.jpg",
	  "Text": "",
	  "Link": "",
	  "Type": "",
	  "Artists": ""
	},
	{
	  "Name": "Widuz",
	  "Image": "Widuz.jpg",
	  "Text": "",
	  "Link": "",
	  "Type": "",
	  "Artists": ""
	},
	{
	  "Name": "Chinguaga",
	  "Image": "Chinguaga.png",
	  "Text": "",
	  "Link": "",
	  "Type": "",
	  "Artists": ""
	},
	{
	  "Name": "Lorca",
	  "Image": "",
	  "Text": "",
	  "Link": "",
	  "Type": "",
	  "Artists": ""
	},
	{
	  "Name": "Scheure & Qualude",
	  "Image": "ScheureQualude.jpg",
	  "Text": "",
	  "Link": "",
	  "Type": "",
	  "Artists": ""
	},
	{
	  "Name": "Candy Andy",
	  "Image": "CandyAndy.PNG",
	  "Text": "",
	  "Link": "https://soundcloud.com/candyandy",
	  "Type": "",
	  "Artists": ""
	},
	{
	  "Name": "Dimensions",
	  "Image": "Dimensions.jpg",
	  "Text": "",
	  "Link": "",
	  "Type": "",
	  "Artists": ""
	},
	{
	  "Name": "Whadjadoc",
	  "Image": "Whandjadoc.JPG",
	  "Text": "",
	  "Link": "",
	  "Type": "",
	  "Artists": ""
	},
	{
	  "Name": "Morioun b2b Aurifex",
	  "Image": "Moriounb2bAurifex.jpg",
	  "Text": "",
	  "Link": "",
	  "Type": "",
	  "Artists": ""
	},
	{
	  "Name": "SODAKIDS",
	  "Image": "SODAKIDS.jpg",
	  "Text": "",
	  "Link": "https://soundcloud.com/sodakids",
	  "Type": "",
	  "Artists": ""
	},
	{
	  "Name": "Paraçek",
	  "Image": "Paracek.JPG",
	  "Text": "",
	  "Link": "https://soundcloud.com/the_kidzwanttechno",
	  "Type": "",
	  "Artists": ""
	},
	{
	  "Name": "IMBALANCE",
	  "Image": "IMBALANCE.jpg",
	  "Text": "",
	  "Link": "https://soundcloud.com/imbalancedj",
	  "Type": "",
	  "Artists": ""
	},
	{
	  "Name": "Mbius",
	  "Image": "Mbius.jpg",
	  "Text": "",
	  "Link": "https://soundcloud.com/mbius0341",
	  "Type": "",
	  "Artists": ""
	},
	{
	  "Name": "just go",
	  "Image": "justgo.jpg",
	  "Text": "",
	  "Link": "https://soundcloud.com/just_go_fun",
	  "Type": "",
	  "Artists": ""
	},
	{
	  "Name": "T-Data",
	  "Image": "T-Data.png",
	  "Text": "",
	  "Link": "https://www.instagram.com/t__earz/",
	  "Type": "",
	  "Artists": ""
	},
	{
	  "Name": "FM Pause b2b DJ Ion",
	  "Image": "",
	  "Text": "",
	  "Link": "",
	  "Type": "multiple",
	  "Artists": [{
		"Name": "FM Pause",
		"Image": "FMPause.jpg",
		"Text": "",
		"Link": "https://soundcloud.com/fmpause,https://www.instagram.com/pausenfm/",
		"Type": "",
		"Artists": ""
	  },
	  {
		"Name": "DJ Ion",
		"Image": "DJIon.jpg",
		"Text": "",
		"Link": "https://soundcloud.com/dj_ion,https://www.instagram.com/dj_ion.121/",
		"Type": "",
		"Artists": ""
	  }]
	},
	{
	  "Name": "Konstantin Unwohl",
	  "Image": "KonstantinUnwohl.jpg",
	  "Text": "",
	  "Link": "https://konstantinunwohl.bandcamp.com/,http://orden-agency.com/",
	  "Type": "",
	  "Artists": ""
	},
	{
	  "Name": "Malte Magnum",
	  "Image": "MalteMagnum.png",
	  "Text": "",
	  "Link": "",
	  "Type": "",
	  "Artists": ""
	},
	{
	  "Name": "Shane Lizard & DJ YumYum",
	  "Image": "1.jpeg",
	  "Text": "",
	  "Link": "https://soundcloud.com/shanelizrd",
	  "Type": "multiple",
	  "Artists": [{
		"Name": "Shane Lizard",
		"Image": "1.jpeg",
		"Text": "",
		"Link": "https://soundcloud.com/shanelizrd",
		"Type": "",
		"Artists": ""
	  },
	  {
		"Name": "DJ YumYum",
		"Image": "1.jpeg",
		"Text": "",
		"Link": "https://soundcloud.com/djyum-yum",
		"Type": "",
		"Artists": ""
	  }]
	},
	{
	  "Name": "Solaris",
	  "Image": "Solaris.jpg",
	  "Text": "",
	  "Link": "https://soundcloud.com/solarisifz",
	  "Type": "",
	  "Artists": ""
	},
	{
	  "Name": "Salomo & Reece Walker (Carmel)",
	  "Image": "SalomoCarmel.jpg",
	  "Text": "",
	  "Link": "",
	  "Type": "multiple",
	  "Artists": [{
		"Name": "Reece Walker (Carmel)",
		"Image": "SalomoCarmel.jpg",
		"Text": "",
		"Link": "https://soundcloud.com/reece-walker",
		"Type": "",
		"Artists": ""
	  },
	  {
		"Name": "Salomo",
		"Image": "SalomoCarmel.jpg",
		"Text": "",
		"Link": "https://soundcloud.com/salomo",
		"Type": "",
		"Artists": ""
	  }]
	},
	{
	  "Name": "DJ Sweet6teen",
	  "Image": "DJSweet6teen.JPG",
	  "Text": "",
	  "Link": "https://instagram.com/djsweet6teen",
	  "Type": "",
	  "Artists": ""
	},
	{
	  "Name": "Tinkah",
	  "Image": "Tinkah.JPG",
	  "Text": "",
	  "Link": "https://soundcloud.com/tinkah-le",
	  "Type": "",
	  "Artists": ""
	},
	{
	  "Name": "Sparlight Express",
	  "Image": "SparlightExpress.jpg",
	  "Text": "",
	  "Link": "https://sparlightexpress-freunde.club/,https://www.instagram.com/sparlightexpress/,https://www.facebook.com/sparlight.express",
	  "Type": "",
	  "Artists": ""
	},
	{
	  "Name": "MALUGI",
	  "Image": "MalugibyNilsVomLande.jpg",
	  "Text": "",
	  "Link": "https://soundcloud.com/malugienergy",
	  "Type": "",
	  "Artists": ""
	},
	{
	  "Name": "Tayo",
	  "Image": "Tayo.png",
	  "Text": "",
	  "Link": "https://soundcloud.com/don139",
	  "Type": "",
	  "Artists": ""
	},
	{
	  "Name": "atte pc + micina",
	  "Image": "attepc.jpeg",
	  "Text": "",
	  "Link": "",
	  "Type": "multiple",
	  "Artists": [{
		"Name": "atte pc",
		"Image": "attepc.jpeg",
		"Text": "",
		"Link": "https://soundcloud.com/atte-pc",
		"Type": "",
		"Artists": ""
	  },
	  {
		"Name": "micina",
		"Image": "micina.JPG",
		"Text": "",
		"Link": "https://soundcloud.com/djmicina,https://www.instagram.com/teufelskind__666/",
		"Type": "",
		"Artists": ""
	  }]
	},
	{
	  "Name": "Leeza b2b Bunny Tsukino",
	  "Image": "BunnyTsukinob2bLeeza.JPG",
	  "Text": "",
	  "Link": "",
	  "Type": "multiple",
	  "Artists": [{
		"Name": "Leeza",
		"Image": "BunnyTsukinob2bLeeza.JPG",
		"Text": "",
		"Link": "https://soundcloud.com/l_eeza",
		"Type": "",
		"Artists": ""
	  },
	  {
		"Name": "Bunny Tsukino",
		"Image": "BunnyTsukinob2bLeeza.JPG",
		"Text": "",
		"Link": "https://soundcloud.com/bunny_tsukino",
		"Type": "",
		"Artists": ""
	  }]
	},
	{
	  "Name": "KAWA KAWA",
	  "Image": "KAWAKAWA.jpeg",
	  "Text": "",
	  "Link": "https://soundcloud.com/kawa-kawa-sound",
	  "Type": "",
	  "Artists": ""
	},
	{
	  "Name": "PJ b2b Lucie Vuittong",
	  "Image": "PJb2bLucieVuittong.JPG",
	  "Text": "",
	  "Link": "",
	  "Type": "multiple",
	  "Artists": [{
		"Name": "PJ",
		"Image": "PJb2bLucieVuittong.JPG",
		"Text": "",
		"Link": "https://soundcloud.com/pj_ptrkspcy",
		"Type": "",
		"Artists": ""
	  },
	  {
		"Name": "Lucie Vuittong",
		"Image": "PJb2bLucieVuittong.JPG",
		"Text": "",
		"Link": "https://soundcloud.com/lucievuittong",
		"Type": "",
		"Artists": ""
	  }]
	},
	{
	  "Name": "solín",
	  "Image": "solín.jpg",
	  "Text": "",
	  "Link": "https://soundcloud.com/simonsolin",
	  "Type": "",
	  "Artists": ""
	},
	{
	  "Name": "kunstlicht",
	  "Image": "Kunstlicht.jpg",
	  "Text": "",
	  "Link": "soundcloud.com/kunstlicht",
	  "Type": "",
	  "Artists": ""
	},
	{
	  "Name": "Moritz Mueller",
	  "Image": "Moritz_Müller.jpg",
	  "Text": "",
	  "Link": "https://www.instagram.com/moritzmueller00/",
	  "Type": "",
	  "Artists": ""
	},
	{
	  "Name": "stoker",
	  "Image": "stoker.jpg",
	  "Text": "",
	  "Link": "https://soundcloud.com/stokerrr,https://www.instagram.com/sophiarrr/",
	  "Type": "",
	  "Artists": ""
	},
	{
	  "Name": "Bastian Vossen",
	  "Image": "BastianVossen.jpg",
	  "Text": "",
	  "Link": "https://soundcloud.com/bastianvossen",
	  "Type": "",
	  "Artists": ""
	},
	{
	  "Name": "HÖRMAN & WÖRNMAN THE EA$TGERMAN",
	  "Image": "HörmanWörn.jpg",
	  "Text": "",
	  "Link": "",
	  "Type": "",
	  "Artists": ""
	},
	{
	  "Name": ":MUMM",
	  "Image": "",
	  "Text": "",
	  "Link": "https://soundcloud.com/m_mm-dj,https://www.instagram.com/m_mm.dj/",
	  "Type": "",
	  "Artists": ""
	},
	{
	  "Name": "Sakin",
	  "Image": "Sakin.jpg",
	  "Text": "",
	  "Link": "https://www.instagram.com/saaakin_/",
	  "Type": "",
	  "Artists": ""
	},
	{
	  "Name": "Loy Bonheur",
	  "Image": "LoyBonheur.jpg",
	  "Text": "",
	  "Link": "www.soundcloud.com/loybonheur",
	  "Type": "",
	  "Artists": ""
	},
	{
	  "Name": "Zwei Rocker",
	  "Image": "ZweiRocker.jpeg",
	  "Text": "",
	  "Link": "https://soundcloud.com/zweirocker",
	  "Type": "",
	  "Artists": ""
	},
	{
	  "Name": "Dj Übergang",
	  "Image": "",
	  "Text": "",
	  "Link": "",
	  "Type": "",
	  "Artists": ""
	},
	{
	  "Name": "VAK - Leipziger Kollektive Podiumsdiskussion",
	  "Image": "",
	  "Text": "",
	  "Link": "https://www.instagram.com/vak.leipzigerkollektive/,https://www.facebook.com/vak.leipzig,https://www.instagram.com/fem_vak/,https://vak.wtf/",
	  "Type": "",
	  "Artists": ""
	},
	{
	  "Name": "Svenedikt Lost",
	  "Image": "svenediktlost.jpg",
	  "Text": "",
	  "Link": "https://soundcloud.com/svenediktlost/tracks,https://www.facebook.com/SvenediktLost/",
	  "Type": "",
	  "Artists": ""
	},
	{
	  "Name": "LOVE PIT",
	  "Image": "",
	  "Text": "",
	  "Link": "https://www.instagram.com/ireneundso/",
	  "Type": "",
	  "Artists": ""
	},
	{
	  "Name": "Das Märchen der Dämmerung",
	  "Image": "DasMärchenderDämmerung.jpg",
	  "Text": "",
	  "Link": "www.instagram.com/schaufenster_geschichten",
	  "Type": "",
	  "Artists": ""
	},
	{
	  "Name": "Metaware",
	  "Image": "",
	  "Text": "",
	  "Link": "https://www.instagram.com/meta.ware/?hl=de,https://www.facebook.com/metaware.weimar/,https://soundcloud.com/metaware_weimar",
	  "Type": "",
	  "Artists": ""
	},
	{
	  "Name": "Leserkanone",
	  "Image": "leserkanone.jpg",
	  "Text": "",
	  "Link": "https://www.youtube.com/yuggothianrecords,https://soundcloud.com/josua-karlson",
	  "Type": "",
	  "Artists": ""
	},
	{
	  "Name": "Hörspiel auf Verlangen",
	  "Image": "",
	  "Text": "",
	  "Link": "https://hoeren.kulturagitator.de/,https://www.facebook.com/hoerspielaufverlangen,https://www.instagram.com/hoerspiel_auf_verlangen/,https://hoerspielaufverlangen.bandcamp.com",
	  "Type": "",
	  "Artists": ""
	},
	{
	  "Name": "Philipp Matalla",
	  "Image": "PhilippMatalla.jpg",
	  "Text": "",
	  "Link": "https://philippmatalla.bandcamp.com",
	  "Type": "",
	  "Artists": ""
	},
	{
	  "Name": "DJ Flatterband",
	  "Image": "Flatterband.jpg",
	  "Text": "",
	  "Link": "https://soundcloud.com/user-756676719",
	  "Type": "",
	  "Artists": ""
	},
	{
	  "Name": "Scherbe",
	  "Image": "Scherbe.jpg",
	  "Text": "",
	  "Link": "https://soundcloud.com/scherbe",
	  "Type": "",
	  "Artists": ""
	},
	{
	  "Name": "Tim Rosenbaum",
	  "Image": "TimRosenbaum.png",
	  "Text": "",
	  "Link": "https://soundcloud.com/timrosenbaum",
	  "Type": "",
	  "Artists": ""
	},
	{
	  "Name": "Hilde Pank",
	  "Image": "HildePank.png",
	  "Text": "",
	  "Link": "https://www.mixcloud.com/Pank_Pinther/",
	  "Type": "",
	  "Artists": ""
	},
	{
	  "Name": "U-I",
	  "Image": "U-I.jpg",
	  "Text": "",
	  "Link": "https://www.instagram.com/dopamindan/",
	  "Type": "",
	  "Artists": ""
	},
	{
	  "Name": "Kali Avaaz",
	  "Image": "KaliAvaaz.JPG",
	  "Text": "",
	  "Link": "https://soundcloud.com/kaliavaaz",
	  "Type": "",
	  "Artists": ""
	},
	{
	  "Name": "ahabzutun",
	  "Image": "ahabzutun.png",
	  "Text": "",
	  "Link": "https://soundcloud.com/ahabzutun",
	  "Type": "",
	  "Artists": ""
	},
	{
	  "Name": "JJ Kramer",
	  "Image": "JJKramer.jpg",
	  "Text": "",
	  "Link": "https://jjkramer.bandcamp.com",
	  "Type": "",
	  "Artists": ""
	},
	{
	  "Name": "Letkidbe",
	  "Image": "Letkidbe.png",
	  "Text": "",
	  "Link": "https://soundcloud.com/letkidbe",
	  "Type": "",
	  "Artists": ""
	},
	{
	  "Name": "DJ Durbin & Kaep (Row Records)",
	  "Image": "DJDurbin.jpg",
	  "Text": "",
	  "Link": "",
	  "Type": "multiple",
	  "Artists": [{
		"Name": "DJ Durbin",
		"Image": "DJDurbin.jpg",
		"Text": "",
		"Link": "https://soundcloud.com/djdurbin",
		"Type": "",
		"Artists": ""
	  },
	  {
		"Name": "Kaep (Row Records)",
		"Image": "Kaep.jpg",
		"Text": "",
		"Link": "https://soundcloud.com/djkaep",
		"Type": "",
		"Artists": ""
	  }]
	},
	{
	  "Name": "Glenn Astro",
	  "Image": "GlennAstro_2vonSedaKaraoglu_.jpg",
	  "Text": "",
	  "Link": "https://soundcloud.com/glenn-astro",
	  "Type": "",
	  "Artists": ""
	},
	{
	  "Name": "Ray Kandinski",
	  "Image": "RayKandinski_Portrait_new.png",
	  "Text": "",
	  "Link": "https://www.instagram.com/raykandinski/",
	  "Type": "",
	  "Artists": ""
	},
	{
	  "Name": "Schmeichel",
	  "Image": "Schmeichel.jpg",
	  "Text": "",
	  "Link": "soundcloud.com/schmeichel34,schmeichel.bandcamp.com",
	  "Type": "",
	  "Artists": ""
	},
	{
	  "Name": "Lea Legrand",
	  "Image": "LeaLegrand.jpeg",
	  "Text": "",
	  "Link": "https://soundcloud.com/lealegrand",
	  "Type": "",
	  "Artists": ""
	},
	{
	  "Name": "Miss Take",
	  "Image": "misstake.jpg",
	  "Text": "",
	  "Link": "https://soundcloud.com/mizz_take",
	  "Type": "",
	  "Artists": ""
	},
	{
	  "Name": "Vanaenae",
	  "Image": "Vanessa_Rauche.jpg",
	  "Text": "",
	  "Link": "www.soundcloud.com/vanaenae_r,https://www.mixcloud.com/musicofcolor/,https://www.instagram.com/vanaenae_r/",
	  "Type": "",
	  "Artists": ""
	},
	{
	  "Name": "goldi",
	  "Image": "goldi.jpeg",
	  "Text": "",
	  "Link": "https://soundcloud.com/goldi_zweitereihe",
	  "Type": "",
	  "Artists": ""
	},
	{
	  "Name": "Mønarch",
	  "Image": "IMG_3097.jpg",
	  "Text": "",
	  "Link": "https://soundcloud.com/monarchofc",
	  "Type": "",
	  "Artists": ""
	},
	{
	  "Name": "Jlululu",
	  "Image": "Jlululu.jpg",
	  "Text": "",
	  "Link": "https://soundcloud.com/jlululu",
	  "Type": "",
	  "Artists": ""
	},
	{
	  "Name": "phoebe",
	  "Image": "Phoebe.png",
	  "Text": "",
	  "Link": "https://soundcloud.com/patricia-balan",
	  "Type": "",
	  "Artists": ""
	},
	{
	  "Name": "eves120",
	  "Image": "eves120.jpg",
	  "Text": "",
	  "Link": "https://soundcloud.com/eves120",
	  "Type": "",
	  "Artists": ""
	},
	{
	  "Name": "Yowlandi x Coco Cobra",
	  "Image": "",
	  "Text": "",
	  "Link": "",
	  "Type": "multiple",
	  "Artists": [{
		"Name": "Yowlandi",
		"Image": "Yowlandi.jpg",
		"Text": "",
		"Link": "https://www.instagram.com/yowlandi",
		"Type": "",
		"Artists": ""
	  },
	  {
		"Name": "Coco Cobra",
		"Image": "CocoCobra-Foto-ChristianWeidner2021.jpg",
		"Text": "",
		"Link": "https://www.instagram.com/coco__cobra",
		"Type": "",
		"Artists": ""
	  }]
	},
	{
	  "Name": "Palermo",
	  "Image": "86347ba9-9cdc-450c-a3cf-519cd8a019ca.JPG",
	  "Text": "",
	  "Link": "https://soundcloud.com/claus-hahn",
	  "Type": "",
	  "Artists": ""
	},
	{
	  "Name": "Klaus.wav",
	  "Image": "Klaus.wav.png",
	  "Text": "",
	  "Link": "https://www.instagram.com/klaus.wav/",
	  "Type": "",
	  "Artists": ""
	},
	{
	  "Name": "D.caprio",
	  "Image": "",
	  "Text": "",
	  "Link": "https://m.soundcloud.com/user-849249727",
	  "Type": "",
	  "Artists": ""
	},
	{
	  "Name": "DJ Purpur b2b Pelle",
	  "Image": "Aron.jpg",
	  "Text": "",
	  "Link": "",
	  "Type": "multiple",
	  "Artists": [{
		"Name": "DJ Purpur",
		"Image": "Aron.jpg",
		"Text": "",
		"Link": "https://soundcloud.com/djpurpur",
		"Type": "",
		"Artists": ""
	  },
	  {
		"Name": "Pelle",
		"Image": "pelle.jpg",
		"Text": "",
		"Link": "https://soundcloud.com/richard-wetzig",
		"Type": "",
		"Artists": ""
	  }]
	},
	{
	  "Name": "thinh",
	  "Image": "thinh.jpg",
	  "Text": "",
	  "Link": "https://soundcloud.com/thinh",
	  "Type": "",
	  "Artists": ""
	},
	{
	  "Name": "Feuerbach (yetunseen, dj-balduin, glyk-musik)",
	  "Image": "Feuerbach_Dj_Pic.jpg",
	  "Text": "",
	  "Link": "https://soundcloud.com/yetunseen\nhttps://soundcloud.com/dj-balduin\nhttps://soundcloud.com/glyk-musik",
	  "Type": "multiple",
	  "Artists": [{
		"Name": "yetunseen",
		"Image": "Feuerbach_Dj_Pic.jpg",
		"Text": "",
		"Link": "https://soundcloud.com/yetunseen",
		"Type": "",
		"Artists": ""
	  },
	  {
		"Name": "dj-balduin",
		"Image": "Feuerbach_Dj_Pic.jpg",
		"Text": "",
		"Link": "https://soundcloud.com/dj-balduin",
		"Type": "",
		"Artists": ""
	  },
	  {
		"Name": "glyk-musik",
		"Image": "Feuerbach_Dj_Pic.jpg",
		"Text": "",
		"Link": "https://soundcloud.com/glyk-musik",
		"Type": "",
		"Artists": ""
	  }]
	},
	{
	  "Name": "gili",
	  "Image": "gili.jpg",
	  "Text": "",
	  "Link": "https://soundcloud.com/giliii,https://www.instagram.com/gili____/",
	  "Type": "",
	  "Artists": ""
	},
	{
	  "Name": "DJ Swagger B2B LUZ1E",
	  "Image": "DJSwagger.jpg",
	  "Text": "",
	  "Link": "",
	  "Type": "multiple",
	  "Artists": [{
		"Name": "DJ Swagger",
		"Image": "DJSwagger.jpg",
		"Text": "",
		"Link": "https://www.instagram.com/therealdjswagger",
		"Type": "",
		"Artists": ""
	  },
	  {
		"Name": "LUZ1E",
		"Image": "LUZ1E.JPG",
		"Text": "",
		"Link": "https://www.instagram.com/l_u_z_1_e/",
		"Type": "",
		"Artists": ""
	  }]
	},
	{
	  "Name": "neelie. aka colluvisol",
	  "Image": "neelie.jpg",
	  "Text": "",
	  "Link": "https://soundcloud.com/neelie-3",
	  "Type": "",
	  "Artists": ""
	},
	{
	  "Name": "Nepomuk",
	  "Image": "nepumuk.jpg",
	  "Text": "",
	  "Link": "https://soundcloud.com/nepo_muk",
	  "Type": "",
	  "Artists": ""
	},
	{
	  "Name": "Galaxaura aka Unity",
	  "Image": "galaxaura.jpg",
	  "Text": "",
	  "Link": "https://soundcloud.com/galaxaura",
	  "Type": "",
	  "Artists": ""
	},
	{
	  "Name": "Super Joy Club",
	  "Image": "Promobildgross.png",
	  "Text": "",
	  "Link": "https://www.instagram.com/super_joy_club_band,https://www.youtube.com/channel/UCorjbwrtp9tkk8YWdVzQEgg",
	  "Type": "",
	  "Artists": ""
	}
  ]